pkcegen/__init__.py
pkcegen-1.0.1.dist-info/LICENSE
pkcegen-1.0.1.dist-info/METADATA
pkcegen-1.0.1.dist-info/WHEEL
pkcegen-1.0.1.dist-info/top_level.txt
pkcegen-1.0.1.dist-info/RECORD
