Metadata-Version: 2.1
Name: pkcegen
Version: 1.0.1
Summary: A flexible and customizable PKCE generator for OAuth2 authentication.
Home-page: https://github.com/70L0-0j0/pkcegen
Author: 70L0-0j0
Author-email: 70L0-0j0@lamia.xyz
Classifier: Programming Language :: Python :: 3
Classifier: License :: OSI Approved :: MIT License
Classifier: Operating System :: OS Independent
Requires-Python: >=3.6
License-File: LICENSE
